defillamaAPI/__init__.py
defillamaAPI/__version__.py
defillamaAPI/abidecoder.py
defillamaAPI/bridges.py
defillamaAPI/coins.py
defillamaAPI/defillamaAPI.py
defillamaAPI/feesandrevenue.py
defillamaAPI/stablecoins.py
defillamaAPI/tvl.py
defillamaAPI/volumes.py
defillamaAPI/yields.py
defillamaAPI-0.0.4.dist-info/METADATA
defillamaAPI-0.0.4.dist-info/WHEEL
defillamaAPI-0.0.4.dist-info/top_level.txt
defillamaAPI-0.0.4.dist-info/RECORD
